{
  "comparisons": {
    "full_trace_belief_vs_belief_with_shuffled_gallery": {
      "OOD_confuser": {
        "MRR": {
          "bootstrap_win_rate": 0.8539518900343642,
          "ci95_high": 0.5798116259456465,
          "ci95_low": 0.4998020278690382,
          "count": 582,
          "mean_delta": 0.5397010407790327,
          "zero_excluded": true
        },
        "false_confuser_rate": {
          "bootstrap_win_rate": 0.42955326460481097,
          "ci95_high": 0.40378006872852235,
          "ci95_low": 0.3006872852233677,
          "count": 582,
          "mean_delta": 0.3539518900343643,
          "zero_excluded": true
        },
        "false_reacquisition_rate": {
          "bootstrap_win_rate": 0.42955326460481097,
          "ci95_high": 0.40378006872852235,
          "ci95_low": 0.3006872852233677,
          "count": 582,
          "mean_delta": 0.3539518900343643,
          "zero_excluded": true
        },
        "top1": {
          "bootstrap_win_rate": 0.42955326460481097,
          "ci95_high": 0.40378006872852235,
          "ci95_low": 0.3006872852233677,
          "count": 582,
          "mean_delta": 0.3539518900343643,
          "zero_excluded": true
        }
      },
      "all_reacquisition_items": {
        "MRR": {
          "bootstrap_win_rate": 0.871868978805395,
          "ci95_high": 0.599501463068314,
          "ci95_low": 0.540135649793227,
          "count": 1038,
          "mean_delta": 0.5692640784931562,
          "zero_excluded": true
        },
        "false_confuser_rate": {
          "bootstrap_win_rate": 0.4605009633911368,
          "ci95_high": 0.4344894026974952,
          "ci95_low": 0.3631984585741811,
          "count": 1038,
          "mean_delta": 0.3978805394990366,
          "zero_excluded": true
        },
        "false_reacquisition_rate": {
          "bootstrap_win_rate": 0.4605009633911368,
          "ci95_high": 0.4344894026974952,
          "ci95_low": 0.3631984585741811,
          "count": 1038,
          "mean_delta": 0.3978805394990366,
          "zero_excluded": true
        },
        "top1": {
          "bootstrap_win_rate": 0.4605009633911368,
          "ci95_high": 0.4344894026974952,
          "ci95_low": 0.3631984585741811,
          "count": 1038,
          "mean_delta": 0.3978805394990366,
          "zero_excluded": true
        }
      },
      "appearance_similar_confuser": {
        "MRR": {
          "bootstrap_win_rate": 0.8685897435897436,
          "ci95_high": 0.5963897792022792,
          "ci95_low": 0.5224732221126452,
          "count": 624,
          "mean_delta": 0.559936435537397,
          "zero_excluded": true
        },
        "false_confuser_rate": {
          "bootstrap_win_rate": 0.4391025641025641,
          "ci95_high": 0.4166666666666667,
          "ci95_low": 0.3173076923076923,
          "count": 624,
          "mean_delta": 0.3685897435897436,
          "zero_excluded": true
        },
        "false_reacquisition_rate": {
          "bootstrap_win_rate": 0.4391025641025641,
          "ci95_high": 0.4166666666666667,
          "ci95_low": 0.3173076923076923,
          "count": 624,
          "mean_delta": 0.3685897435897436,
          "zero_excluded": true
        },
        "top1": {
          "bootstrap_win_rate": 0.4391025641025641,
          "ci95_high": 0.4166666666666667,
          "ci95_low": 0.3173076923076923,
          "count": 624,
          "mean_delta": 0.3685897435897436,
          "zero_excluded": true
        }
      },
      "crossing_or_overlap_confuser": {
        "MRR": {
          "bootstrap_win_rate": 0.8904109589041096,
          "ci95_high": 0.5508715274974954,
          "ci95_low": 0.45401194949140156,
          "count": 438,
          "mean_delta": 0.503301628940402,
          "zero_excluded": true
        },
        "false_confuser_rate": {
          "bootstrap_win_rate": 0.4178082191780822,
          "ci95_high": 0.3972602739726027,
          "ci95_low": 0.2785388127853881,
          "count": 438,
          "mean_delta": 0.3378995433789954,
          "zero_excluded": true
        },
        "false_reacquisition_rate": {
          "bootstrap_win_rate": 0.4178082191780822,
          "ci95_high": 0.3972602739726027,
          "ci95_low": 0.2785388127853881,
          "count": 438,
          "mean_delta": 0.3378995433789954,
          "zero_excluded": true
        },
        "top1": {
          "bootstrap_win_rate": 0.4178082191780822,
          "ci95_high": 0.3972602739726027,
          "ci95_low": 0.2785388127853881,
          "count": 438,
          "mean_delta": 0.3378995433789954,
          "zero_excluded": true
        }
      },
      "long_gap_persistence": {
        "MRR": {
          "bootstrap_win_rate": 0.8393574297188755,
          "ci95_high": 0.568908969210174,
          "ci95_low": 0.4851357812201186,
          "count": 498,
          "mean_delta": 0.5271658060814687,
          "zero_excluded": true
        },
        "false_confuser_rate": {
          "bootstrap_win_rate": 0.42369477911646586,
          "ci95_high": 0.40562248995983935,
          "ci95_low": 0.2971887550200803,
          "count": 498,
          "mean_delta": 0.3493975903614458,
          "zero_excluded": true
        },
        "false_reacquisition_rate": {
          "bootstrap_win_rate": 0.42369477911646586,
          "ci95_high": 0.40562248995983935,
          "ci95_low": 0.2971887550200803,
          "count": 498,
          "mean_delta": 0.3493975903614458,
          "zero_excluded": true
        },
        "top1": {
          "bootstrap_win_rate": 0.42369477911646586,
          "ci95_high": 0.40562248995983935,
          "ci95_low": 0.2971887550200803,
          "count": 498,
          "mean_delta": 0.3493975903614458,
          "zero_excluded": true
        }
      },
      "occlusion_and_long_gap": {
        "MRR": {
          "bootstrap_win_rate": 0.8393574297188755,
          "ci95_high": 0.568908969210174,
          "ci95_low": 0.4851357812201186,
          "count": 498,
          "mean_delta": 0.5271658060814687,
          "zero_excluded": true
        },
        "false_confuser_rate": {
          "bootstrap_win_rate": 0.42369477911646586,
          "ci95_high": 0.40562248995983935,
          "ci95_low": 0.2971887550200803,
          "count": 498,
          "mean_delta": 0.3493975903614458,
          "zero_excluded": true
        },
        "false_reacquisition_rate": {
          "bootstrap_win_rate": 0.42369477911646586,
          "ci95_high": 0.40562248995983935,
          "ci95_low": 0.2971887550200803,
          "count": 498,
          "mean_delta": 0.3493975903614458,
          "zero_excluded": true
        },
        "top1": {
          "bootstrap_win_rate": 0.42369477911646586,
          "ci95_high": 0.40562248995983935,
          "ci95_low": 0.2971887550200803,
          "count": 498,
          "mean_delta": 0.3493975903614458,
          "zero_excluded": true
        }
      },
      "occlusion_reappearance": {
        "MRR": {
          "bootstrap_win_rate": 0.871868978805395,
          "ci95_high": 0.599501463068314,
          "ci95_low": 0.540135649793227,
          "count": 1038,
          "mean_delta": 0.5692640784931562,
          "zero_excluded": true
        },
        "false_confuser_rate": {
          "bootstrap_win_rate": 0.4605009633911368,
          "ci95_high": 0.4344894026974952,
          "ci95_low": 0.3631984585741811,
          "count": 1038,
          "mean_delta": 0.3978805394990366,
          "zero_excluded": true
        },
        "false_reacquisition_rate": {
          "bootstrap_win_rate": 0.4605009633911368,
          "ci95_high": 0.4344894026974952,
          "ci95_low": 0.3631984585741811,
          "count": 1038,
          "mean_delta": 0.3978805394990366,
          "zero_excluded": true
        },
        "top1": {
          "bootstrap_win_rate": 0.4605009633911368,
          "ci95_high": 0.4344894026974952,
          "ci95_low": 0.3631984585741811,
          "count": 1038,
          "mean_delta": 0.3978805394990366,
          "zero_excluded": true
        }
      },
      "spatially_close_confuser": {
        "MRR": {
          "bootstrap_win_rate": 0.8979885057471264,
          "ci95_high": 0.570316659817222,
          "ci95_low": 0.5001860371359996,
          "count": 696,
          "mean_delta": 0.5364099878895606,
          "zero_excluded": true
        },
        "false_confuser_rate": {
          "bootstrap_win_rate": 0.40804597701149425,
          "ci95_high": 0.39080459770114945,
          "ci95_low": 0.2988505747126437,
          "count": 696,
          "mean_delta": 0.34339080459770116,
          "zero_excluded": true
        },
        "false_reacquisition_rate": {
          "bootstrap_win_rate": 0.40804597701149425,
          "ci95_high": 0.39080459770114945,
          "ci95_low": 0.2988505747126437,
          "count": 696,
          "mean_delta": 0.34339080459770116,
          "zero_excluded": true
        },
        "top1": {
          "bootstrap_win_rate": 0.40804597701149425,
          "ci95_high": 0.39080459770114945,
          "ci95_low": 0.2988505747126437,
          "count": 696,
          "mean_delta": 0.34339080459770116,
          "zero_excluded": true
        }
      }
    },
    "full_trace_belief_vs_belief_with_shuffled_trace": {
      "OOD_confuser": {
        "MRR": {
          "bootstrap_win_rate": 0.8848797250859106,
          "ci95_high": 0.6084463074153796,
          "ci95_low": 0.5325006608511763,
          "count": 582,
          "mean_delta": 0.5706288758305791,
          "zero_excluded": true
        },
        "false_confuser_rate": {
          "bootstrap_win_rate": 0.44673539518900346,
          "ci95_high": 0.43470790378006874,
          "ci95_low": 0.33505154639175255,
          "count": 582,
          "mean_delta": 0.3848797250859107,
          "zero_excluded": true
        },
        "false_reacquisition_rate": {
          "bootstrap_win_rate": 0.44673539518900346,
          "ci95_high": 0.43470790378006874,
          "ci95_low": 0.33505154639175255,
          "count": 582,
          "mean_delta": 0.3848797250859107,
          "zero_excluded": true
        },
        "top1": {
          "bootstrap_win_rate": 0.44673539518900346,
          "ci95_high": 0.43470790378006874,
          "ci95_low": 0.33505154639175255,
          "count": 582,
          "mean_delta": 0.3848797250859107,
          "zero_excluded": true
        }
      },
      "all_reacquisition_items": {
        "MRR": {
          "bootstrap_win_rate": 0.8901734104046243,
          "ci95_high": 0.6149575912531429,
          "ci95_low": 0.55993617561034,
          "count": 1038,
          "mean_delta": 0.5875685100923854,
          "zero_excluded": true
        },
        "false_confuser_rate": {
          "bootstrap_win_rate": 0.46917148362235067,
          "ci95_high": 0.45183044315992293,
          "ci95_low": 0.3805394990366089,
          "count": 1038,
          "mean_delta": 0.4161849710982659,
          "zero_excluded": true
        },
        "false_reacquisition_rate": {
          "bootstrap_win_rate": 0.46917148362235067,
          "ci95_high": 0.45183044315992293,
          "ci95_low": 0.3805394990366089,
          "count": 1038,
          "mean_delta": 0.4161849710982659,
          "zero_excluded": true
        },
        "top1": {
          "bootstrap_win_rate": 0.46917148362235067,
          "ci95_high": 0.45183044315992293,
          "ci95_low": 0.3805394990366089,
          "count": 1038,
          "mean_delta": 0.4161849710982659,
          "zero_excluded": true
        }
      },
      "appearance_similar_confuser": {
        "MRR": {
          "bootstrap_win_rate": 0.8830128205128205,
          "ci95_high": 0.610340354090354,
          "ci95_low": 0.5384868781503397,
          "count": 624,
          "mean_delta": 0.574359512460474,
          "zero_excluded": true
        },
        "false_confuser_rate": {
          "bootstrap_win_rate": 0.45032051282051283,
          "ci95_high": 0.4310897435897436,
          "ci95_low": 0.3333333333333333,
          "count": 624,
          "mean_delta": 0.38301282051282054,
          "zero_excluded": true
        },
        "false_reacquisition_rate": {
          "bootstrap_win_rate": 0.45032051282051283,
          "ci95_high": 0.4310897435897436,
          "ci95_low": 0.3333333333333333,
          "count": 624,
          "mean_delta": 0.38301282051282054,
          "zero_excluded": true
        },
        "top1": {
          "bootstrap_win_rate": 0.45032051282051283,
          "ci95_high": 0.4310897435897436,
          "ci95_low": 0.3333333333333333,
          "count": 624,
          "mean_delta": 0.38301282051282054,
          "zero_excluded": true
        }
      },
      "crossing_or_overlap_confuser": {
        "MRR": {
          "bootstrap_win_rate": 0.9223744292237442,
          "ci95_high": 0.5787213308386626,
          "ci95_low": 0.4895540242740957,
          "count": 438,
          "mean_delta": 0.5352650992600367,
          "zero_excluded": true
        },
        "false_confuser_rate": {
          "bootstrap_win_rate": 0.4246575342465753,
          "ci95_high": 0.4246575342465753,
          "ci95_low": 0.3150684931506849,
          "count": 438,
          "mean_delta": 0.3698630136986301,
          "zero_excluded": true
        },
        "false_reacquisition_rate": {
          "bootstrap_win_rate": 0.4246575342465753,
          "ci95_high": 0.4246575342465753,
          "ci95_low": 0.3150684931506849,
          "count": 438,
          "mean_delta": 0.3698630136986301,
          "zero_excluded": true
        },
        "top1": {
          "bootstrap_win_rate": 0.4246575342465753,
          "ci95_high": 0.4246575342465753,
          "ci95_low": 0.3150684931506849,
          "count": 438,
          "mean_delta": 0.3698630136986301,
          "zero_excluded": true
        }
      },
      "long_gap_persistence": {
        "MRR": {
          "bootstrap_win_rate": 0.8433734939759037,
          "ci95_high": 0.5733816217249952,
          "ci95_low": 0.4905335628227194,
          "count": 498,
          "mean_delta": 0.5311818703384968,
          "zero_excluded": true
        },
        "false_confuser_rate": {
          "bootstrap_win_rate": 0.41767068273092367,
          "ci95_high": 0.40763052208835343,
          "ci95_low": 0.30120481927710846,
          "count": 498,
          "mean_delta": 0.3534136546184739,
          "zero_excluded": true
        },
        "false_reacquisition_rate": {
          "bootstrap_win_rate": 0.41767068273092367,
          "ci95_high": 0.40763052208835343,
          "ci95_low": 0.30120481927710846,
          "count": 498,
          "mean_delta": 0.3534136546184739,
          "zero_excluded": true
        },
        "top1": {
          "bootstrap_win_rate": 0.41767068273092367,
          "ci95_high": 0.40763052208835343,
          "ci95_low": 0.30120481927710846,
          "count": 498,
          "mean_delta": 0.3534136546184739,
          "zero_excluded": true
        }
      },
      "occlusion_and_long_gap": {
        "MRR": {
          "bootstrap_win_rate": 0.8433734939759037,
          "ci95_high": 0.5733816217249952,
          "ci95_low": 0.4905335628227194,
          "count": 498,
          "mean_delta": 0.5311818703384968,
          "zero_excluded": true
        },
        "false_confuser_rate": {
          "bootstrap_win_rate": 0.41767068273092367,
          "ci95_high": 0.40763052208835343,
          "ci95_low": 0.30120481927710846,
          "count": 498,
          "mean_delta": 0.3534136546184739,
          "zero_excluded": true
        },
        "false_reacquisition_rate": {
          "bootstrap_win_rate": 0.41767068273092367,
          "ci95_high": 0.40763052208835343,
          "ci95_low": 0.30120481927710846,
          "count": 498,
          "mean_delta": 0.3534136546184739,
          "zero_excluded": true
        },
        "top1": {
          "bootstrap_win_rate": 0.41767068273092367,
          "ci95_high": 0.40763052208835343,
          "ci95_low": 0.30120481927710846,
          "count": 498,
          "mean_delta": 0.3534136546184739,
          "zero_excluded": true
        }
      },
      "occlusion_reappearance": {
        "MRR": {
          "bootstrap_win_rate": 0.8901734104046243,
          "ci95_high": 0.6149575912531429,
          "ci95_low": 0.55993617561034,
          "count": 1038,
          "mean_delta": 0.5875685100923854,
          "zero_excluded": true
        },
        "false_confuser_rate": {
          "bootstrap_win_rate": 0.46917148362235067,
          "ci95_high": 0.45183044315992293,
          "ci95_low": 0.3805394990366089,
          "count": 1038,
          "mean_delta": 0.4161849710982659,
          "zero_excluded": true
        },
        "false_reacquisition_rate": {
          "bootstrap_win_rate": 0.46917148362235067,
          "ci95_high": 0.45183044315992293,
          "ci95_low": 0.3805394990366089,
          "count": 1038,
          "mean_delta": 0.4161849710982659,
          "zero_excluded": true
        },
        "top1": {
          "bootstrap_win_rate": 0.46917148362235067,
          "ci95_high": 0.45183044315992293,
          "ci95_low": 0.3805394990366089,
          "count": 1038,
          "mean_delta": 0.4161849710982659,
          "zero_excluded": true
        }
      },
      "spatially_close_confuser": {
        "MRR": {
          "bootstrap_win_rate": 0.9152298850574713,
          "ci95_high": 0.5877774772564878,
          "ci95_low": 0.5211693782992509,
          "count": 696,
          "mean_delta": 0.5536513671999054,
          "zero_excluded": true
        },
        "false_confuser_rate": {
          "bootstrap_win_rate": 0.41522988505747127,
          "ci95_high": 0.40373563218390807,
          "ci95_low": 0.3175287356321839,
          "count": 696,
          "mean_delta": 0.36063218390804597,
          "zero_excluded": true
        },
        "false_reacquisition_rate": {
          "bootstrap_win_rate": 0.41522988505747127,
          "ci95_high": 0.40373563218390807,
          "ci95_low": 0.3175287356321839,
          "count": 696,
          "mean_delta": 0.36063218390804597,
          "zero_excluded": true
        },
        "top1": {
          "bootstrap_win_rate": 0.41522988505747127,
          "ci95_high": 0.40373563218390807,
          "ci95_low": 0.3175287356321839,
          "count": 696,
          "mean_delta": 0.36063218390804597,
          "zero_excluded": true
        }
      }
    },
    "full_trace_belief_vs_belief_without_trace_prior": {
      "OOD_confuser": {
        "MRR": {
          "bootstrap_win_rate": 0.029209621993127148,
          "ci95_high": -0.0374421492978194,
          "ci95_low": -0.06292093346665287,
          "count": 582,
          "mean_delta": -0.0501221168448122,
          "zero_excluded": true
        },
        "false_confuser_rate": {
          "bootstrap_win_rate": 0.006872852233676976,
          "ci95_high": -0.05670103092783505,
          "ci95_low": -0.10309278350515463,
          "count": 582,
          "mean_delta": -0.07903780068728522,
          "zero_excluded": true
        },
        "false_reacquisition_rate": {
          "bootstrap_win_rate": 0.006872852233676976,
          "ci95_high": -0.05670103092783505,
          "ci95_low": -0.10309278350515463,
          "count": 582,
          "mean_delta": -0.07903780068728522,
          "zero_excluded": true
        },
        "top1": {
          "bootstrap_win_rate": 0.006872852233676976,
          "ci95_high": -0.05670103092783505,
          "ci95_low": -0.10309278350515463,
          "count": 582,
          "mean_delta": -0.07903780068728522,
          "zero_excluded": true
        }
      },
      "all_reacquisition_items": {
        "MRR": {
          "bootstrap_win_rate": 0.029865125240847785,
          "ci95_high": -0.037332021087361625,
          "ci95_low": -0.05560465464649934,
          "count": 1038,
          "mean_delta": -0.04627645961000238,
          "zero_excluded": true
        },
        "false_confuser_rate": {
          "bootstrap_win_rate": 0.00674373795761079,
          "ci95_high": -0.055876685934489405,
          "ci95_low": -0.08959537572254335,
          "count": 1038,
          "mean_delta": -0.07225433526011561,
          "zero_excluded": true
        },
        "false_reacquisition_rate": {
          "bootstrap_win_rate": 0.00674373795761079,
          "ci95_high": -0.055876685934489405,
          "ci95_low": -0.08959537572254335,
          "count": 1038,
          "mean_delta": -0.07225433526011561,
          "zero_excluded": true
        },
        "top1": {
          "bootstrap_win_rate": 0.00674373795761079,
          "ci95_high": -0.055876685934489405,
          "ci95_low": -0.08959537572254335,
          "count": 1038,
          "mean_delta": -0.07225433526011561,
          "zero_excluded": true
        }
      },
      "appearance_similar_confuser": {
        "MRR": {
          "bootstrap_win_rate": 0.00641025641025641,
          "ci95_high": -0.03992610398860399,
          "ci95_low": -0.06281606125356125,
          "count": 624,
          "mean_delta": -0.05125788563288563,
          "zero_excluded": true
        },
        "false_confuser_rate": {
          "bootstrap_win_rate": 0.0,
          "ci95_high": -0.05929487179487179,
          "ci95_low": -0.10256410256410256,
          "count": 624,
          "mean_delta": -0.08012820512820513,
          "zero_excluded": true
        },
        "false_reacquisition_rate": {
          "bootstrap_win_rate": 0.0,
          "ci95_high": -0.05929487179487179,
          "ci95_low": -0.10256410256410256,
          "count": 624,
          "mean_delta": -0.08012820512820513,
          "zero_excluded": true
        },
        "top1": {
          "bootstrap_win_rate": 0.0,
          "ci95_high": -0.05929487179487179,
          "ci95_low": -0.10256410256410256,
          "count": 624,
          "mean_delta": -0.08012820512820513,
          "zero_excluded": true
        }
      },
      "crossing_or_overlap_confuser": {
        "MRR": {
          "bootstrap_win_rate": 0.0593607305936073,
          "ci95_high": -0.024361702900515685,
          "ci95_low": -0.05255270689060643,
          "count": 438,
          "mean_delta": -0.038588200323856466,
          "zero_excluded": true
        },
        "false_confuser_rate": {
          "bootstrap_win_rate": 0.0091324200913242,
          "ci95_high": -0.0365296803652968,
          "ci95_low": -0.0867579908675799,
          "count": 438,
          "mean_delta": -0.06164383561643835,
          "zero_excluded": true
        },
        "false_reacquisition_rate": {
          "bootstrap_win_rate": 0.0091324200913242,
          "ci95_high": -0.0365296803652968,
          "ci95_low": -0.0867579908675799,
          "count": 438,
          "mean_delta": -0.06164383561643835,
          "zero_excluded": true
        },
        "top1": {
          "bootstrap_win_rate": 0.0091324200913242,
          "ci95_high": -0.0365296803652968,
          "ci95_low": -0.0867579908675799,
          "count": 438,
          "mean_delta": -0.06164383561643835,
          "zero_excluded": true
        }
      },
      "long_gap_persistence": {
        "MRR": {
          "bootstrap_win_rate": 0.030120481927710843,
          "ci95_high": -0.027127557850449416,
          "ci95_low": -0.050150602409638555,
          "count": 498,
          "mean_delta": -0.038855421686746994,
          "zero_excluded": true
        },
        "false_confuser_rate": {
          "bootstrap_win_rate": 0.006024096385542169,
          "ci95_high": -0.03614457831325301,
          "ci95_low": -0.0823293172690763,
          "count": 498,
          "mean_delta": -0.05823293172690763,
          "zero_excluded": true
        },
        "false_reacquisition_rate": {
          "bootstrap_win_rate": 0.006024096385542169,
          "ci95_high": -0.03614457831325301,
          "ci95_low": -0.0823293172690763,
          "count": 498,
          "mean_delta": -0.05823293172690763,
          "zero_excluded": true
        },
        "top1": {
          "bootstrap_win_rate": 0.006024096385542169,
          "ci95_high": -0.03614457831325301,
          "ci95_low": -0.0823293172690763,
          "count": 498,
          "mean_delta": -0.05823293172690763,
          "zero_excluded": true
        }
      },
      "occlusion_and_long_gap": {
        "MRR": {
          "bootstrap_win_rate": 0.030120481927710843,
          "ci95_high": -0.027127557850449416,
          "ci95_low": -0.050150602409638555,
          "count": 498,
          "mean_delta": -0.038855421686746994,
          "zero_excluded": true
        },
        "false_confuser_rate": {
          "bootstrap_win_rate": 0.006024096385542169,
          "ci95_high": -0.03614457831325301,
          "ci95_low": -0.0823293172690763,
          "count": 498,
          "mean_delta": -0.05823293172690763,
          "zero_excluded": true
        },
        "false_reacquisition_rate": {
          "bootstrap_win_rate": 0.006024096385542169,
          "ci95_high": -0.03614457831325301,
          "ci95_low": -0.0823293172690763,
          "count": 498,
          "mean_delta": -0.05823293172690763,
          "zero_excluded": true
        },
        "top1": {
          "bootstrap_win_rate": 0.006024096385542169,
          "ci95_high": -0.03614457831325301,
          "ci95_low": -0.0823293172690763,
          "count": 498,
          "mean_delta": -0.05823293172690763,
          "zero_excluded": true
        }
      },
      "occlusion_reappearance": {
        "MRR": {
          "bootstrap_win_rate": 0.029865125240847785,
          "ci95_high": -0.037332021087361625,
          "ci95_low": -0.05560465464649934,
          "count": 1038,
          "mean_delta": -0.04627645961000238,
          "zero_excluded": true
        },
        "false_confuser_rate": {
          "bootstrap_win_rate": 0.00674373795761079,
          "ci95_high": -0.055876685934489405,
          "ci95_low": -0.08959537572254335,
          "count": 1038,
          "mean_delta": -0.07225433526011561,
          "zero_excluded": true
        },
        "false_reacquisition_rate": {
          "bootstrap_win_rate": 0.00674373795761079,
          "ci95_high": -0.055876685934489405,
          "ci95_low": -0.08959537572254335,
          "count": 1038,
          "mean_delta": -0.07225433526011561,
          "zero_excluded": true
        },
        "top1": {
          "bootstrap_win_rate": 0.00674373795761079,
          "ci95_high": -0.055876685934489405,
          "ci95_low": -0.08959537572254335,
          "count": 1038,
          "mean_delta": -0.07225433526011561,
          "zero_excluded": true
        }
      },
      "spatially_close_confuser": {
        "MRR": {
          "bootstrap_win_rate": 0.034482758620689655,
          "ci95_high": -0.03449601766068532,
          "ci95_low": -0.05647308077655404,
          "count": 696,
          "mean_delta": -0.045524375108020786,
          "zero_excluded": true
        },
        "false_confuser_rate": {
          "bootstrap_win_rate": 0.008620689655172414,
          "ci95_high": -0.04310344827586207,
          "ci95_low": -0.08477011494252873,
          "count": 696,
          "mean_delta": -0.06321839080459771,
          "zero_excluded": true
        },
        "false_reacquisition_rate": {
          "bootstrap_win_rate": 0.008620689655172414,
          "ci95_high": -0.04310344827586207,
          "ci95_low": -0.08477011494252873,
          "count": 696,
          "mean_delta": -0.06321839080459771,
          "zero_excluded": true
        },
        "top1": {
          "bootstrap_win_rate": 0.008620689655172414,
          "ci95_high": -0.04310344827586207,
          "ci95_low": -0.08477011494252873,
          "count": 696,
          "mean_delta": -0.06321839080459771,
          "zero_excluded": true
        }
      }
    },
    "full_trace_belief_vs_calibration-only": {
      "OOD_confuser": {
        "MRR": {
          "bootstrap_win_rate": 0.6237113402061856,
          "ci95_high": 0.27841910418721816,
          "ci95_low": 0.21111652154875338,
          "count": 582,
          "mean_delta": 0.2450130376435255,
          "zero_excluded": true
        },
        "false_confuser_rate": {
          "bootstrap_win_rate": 0.40378006872852235,
          "ci95_high": 0.3694158075601375,
          "ci95_low": 0.27147766323024053,
          "count": 582,
          "mean_delta": 0.3230240549828179,
          "zero_excluded": true
        },
        "false_reacquisition_rate": {
          "bootstrap_win_rate": 0.40378006872852235,
          "ci95_high": 0.3694158075601375,
          "ci95_low": 0.27147766323024053,
          "count": 582,
          "mean_delta": 0.3230240549828179,
          "zero_excluded": true
        },
        "top1": {
          "bootstrap_win_rate": 0.40378006872852235,
          "ci95_high": 0.3694158075601375,
          "ci95_low": 0.27147766323024053,
          "count": 582,
          "mean_delta": 0.3230240549828179,
          "zero_excluded": true
        }
      },
      "all_reacquisition_items": {
        "MRR": {
          "bootstrap_win_rate": 0.653179190751445,
          "ci95_high": 0.2909789668857995,
          "ci95_low": 0.24151976735325162,
          "count": 1038,
          "mean_delta": 0.2660651508102989,
          "zero_excluded": true
        },
        "false_confuser_rate": {
          "bootstrap_win_rate": 0.44315992292870904,
          "ci95_high": 0.39980732177263967,
          "ci95_low": 0.3236994219653179,
          "count": 1038,
          "mean_delta": 0.3622350674373796,
          "zero_excluded": true
        },
        "false_reacquisition_rate": {
          "bootstrap_win_rate": 0.44315992292870904,
          "ci95_high": 0.39980732177263967,
          "ci95_low": 0.3236994219653179,
          "count": 1038,
          "mean_delta": 0.3622350674373796,
          "zero_excluded": true
        },
        "top1": {
          "bootstrap_win_rate": 0.44315992292870904,
          "ci95_high": 0.39980732177263967,
          "ci95_low": 0.3236994219653179,
          "count": 1038,
          "mean_delta": 0.3622350674373796,
          "zero_excluded": true
        }
      },
      "appearance_similar_confuser": {
        "MRR": {
          "bootstrap_win_rate": 0.6009615384615384,
          "ci95_high": 0.24079332793275102,
          "ci95_low": 0.17500763125763127,
          "count": 624,
          "mean_delta": 0.2077615271124887,
          "zero_excluded": true
        },
        "false_confuser_rate": {
          "bootstrap_win_rate": 0.3974358974358974,
          "ci95_high": 0.33653846153846156,
          "ci95_low": 0.23557692307692307,
          "count": 624,
          "mean_delta": 0.28525641025641024,
          "zero_excluded": true
        },
        "false_reacquisition_rate": {
          "bootstrap_win_rate": 0.3974358974358974,
          "ci95_high": 0.33653846153846156,
          "ci95_low": 0.23557692307692307,
          "count": 624,
          "mean_delta": 0.28525641025641024,
          "zero_excluded": true
        },
        "top1": {
          "bootstrap_win_rate": 0.3974358974358974,
          "ci95_high": 0.33653846153846156,
          "ci95_low": 0.23557692307692307,
          "count": 624,
          "mean_delta": 0.28525641025641024,
          "zero_excluded": true
        }
      },
      "crossing_or_overlap_confuser": {
        "MRR": {
          "bootstrap_win_rate": 0.547945205479452,
          "ci95_high": 0.253750032948735,
          "ci95_low": 0.17183294547529973,
          "count": 438,
          "mean_delta": 0.21312294238199198,
          "zero_excluded": true
        },
        "false_confuser_rate": {
          "bootstrap_win_rate": 0.3698630136986301,
          "ci95_high": 0.3470319634703196,
          "ci95_low": 0.2374429223744292,
          "count": 438,
          "mean_delta": 0.2922374429223744,
          "zero_excluded": true
        },
        "false_reacquisition_rate": {
          "bootstrap_win_rate": 0.3698630136986301,
          "ci95_high": 0.3470319634703196,
          "ci95_low": 0.2374429223744292,
          "count": 438,
          "mean_delta": 0.2922374429223744,
          "zero_excluded": true
        },
        "top1": {
          "bootstrap_win_rate": 0.3698630136986301,
          "ci95_high": 0.3470319634703196,
          "ci95_low": 0.2374429223744292,
          "count": 438,
          "mean_delta": 0.2922374429223744,
          "zero_excluded": true
        }
      },
      "long_gap_persistence": {
        "MRR": {
          "bootstrap_win_rate": 0.6807228915662651,
          "ci95_high": 0.25925925925925924,
          "ci95_low": 0.19043953592146362,
          "count": 498,
          "mean_delta": 0.22501434308663226,
          "zero_excluded": true
        },
        "false_confuser_rate": {
          "bootstrap_win_rate": 0.42570281124497994,
          "ci95_high": 0.39759036144578314,
          "ci95_low": 0.28714859437751006,
          "count": 498,
          "mean_delta": 0.3413654618473896,
          "zero_excluded": true
        },
        "false_reacquisition_rate": {
          "bootstrap_win_rate": 0.42570281124497994,
          "ci95_high": 0.39759036144578314,
          "ci95_low": 0.28714859437751006,
          "count": 498,
          "mean_delta": 0.3413654618473896,
          "zero_excluded": true
        },
        "top1": {
          "bootstrap_win_rate": 0.42570281124497994,
          "ci95_high": 0.39759036144578314,
          "ci95_low": 0.28714859437751006,
          "count": 498,
          "mean_delta": 0.3413654618473896,
          "zero_excluded": true
        }
      },
      "occlusion_and_long_gap": {
        "MRR": {
          "bootstrap_win_rate": 0.6807228915662651,
          "ci95_high": 0.25925925925925924,
          "ci95_low": 0.19043953592146362,
          "count": 498,
          "mean_delta": 0.22501434308663226,
          "zero_excluded": true
        },
        "false_confuser_rate": {
          "bootstrap_win_rate": 0.42570281124497994,
          "ci95_high": 0.39759036144578314,
          "ci95_low": 0.28714859437751006,
          "count": 498,
          "mean_delta": 0.3413654618473896,
          "zero_excluded": true
        },
        "false_reacquisition_rate": {
          "bootstrap_win_rate": 0.42570281124497994,
          "ci95_high": 0.39759036144578314,
          "ci95_low": 0.28714859437751006,
          "count": 498,
          "mean_delta": 0.3413654618473896,
          "zero_excluded": true
        },
        "top1": {
          "bootstrap_win_rate": 0.42570281124497994,
          "ci95_high": 0.39759036144578314,
          "ci95_low": 0.28714859437751006,
          "count": 498,
          "mean_delta": 0.3413654618473896,
          "zero_excluded": true
        }
      },
      "occlusion_reappearance": {
        "MRR": {
          "bootstrap_win_rate": 0.653179190751445,
          "ci95_high": 0.2909789668857995,
          "ci95_low": 0.24151976735325162,
          "count": 1038,
          "mean_delta": 0.2660651508102989,
          "zero_excluded": true
        },
        "false_confuser_rate": {
          "bootstrap_win_rate": 0.44315992292870904,
          "ci95_high": 0.39980732177263967,
          "ci95_low": 0.3236994219653179,
          "count": 1038,
          "mean_delta": 0.3622350674373796,
          "zero_excluded": true
        },
        "false_reacquisition_rate": {
          "bootstrap_win_rate": 0.44315992292870904,
          "ci95_high": 0.39980732177263967,
          "ci95_low": 0.3236994219653179,
          "count": 1038,
          "mean_delta": 0.3622350674373796,
          "zero_excluded": true
        },
        "top1": {
          "bootstrap_win_rate": 0.44315992292870904,
          "ci95_high": 0.39980732177263967,
          "ci95_low": 0.3236994219653179,
          "count": 1038,
          "mean_delta": 0.3622350674373796,
          "zero_excluded": true
        }
      },
      "spatially_close_confuser": {
        "MRR": {
          "bootstrap_win_rate": 0.6695402298850575,
          "ci95_high": 0.2940289393062644,
          "ci95_low": 0.23018874059332933,
          "count": 696,
          "mean_delta": 0.2623862997648396,
          "zero_excluded": true
        },
        "false_confuser_rate": {
          "bootstrap_win_rate": 0.3793103448275862,
          "ci95_high": 0.34051724137931033,
          "ci95_low": 0.25,
          "count": 696,
          "mean_delta": 0.2959770114942529,
          "zero_excluded": true
        },
        "false_reacquisition_rate": {
          "bootstrap_win_rate": 0.3793103448275862,
          "ci95_high": 0.34051724137931033,
          "ci95_low": 0.25,
          "count": 696,
          "mean_delta": 0.2959770114942529,
          "zero_excluded": true
        },
        "top1": {
          "bootstrap_win_rate": 0.3793103448275862,
          "ci95_high": 0.34051724137931033,
          "ci95_low": 0.25,
          "count": 696,
          "mean_delta": 0.2959770114942529,
          "zero_excluded": true
        }
      }
    },
    "full_trace_belief_vs_frozen_external_teacher_only": {
      "OOD_confuser": {
        "MRR": {
          "bootstrap_win_rate": 0.2663230240549828,
          "ci95_high": 0.014971902347145138,
          "ci95_low": -0.04204901475557385,
          "count": 582,
          "mean_delta": -0.01317219327976836,
          "zero_excluded": false
        },
        "false_confuser_rate": {
          "bootstrap_win_rate": 0.17010309278350516,
          "ci95_high": 0.03436426116838488,
          "ci95_low": -0.06357388316151202,
          "count": 582,
          "mean_delta": -0.015463917525773196,
          "zero_excluded": false
        },
        "false_reacquisition_rate": {
          "bootstrap_win_rate": 0.17010309278350516,
          "ci95_high": 0.03436426116838488,
          "ci95_low": -0.06357388316151202,
          "count": 582,
          "mean_delta": -0.015463917525773196,
          "zero_excluded": false
        },
        "top1": {
          "bootstrap_win_rate": 0.17010309278350516,
          "ci95_high": 0.03436426116838488,
          "ci95_low": -0.06357388316151202,
          "count": 582,
          "mean_delta": -0.015463917525773196,
          "zero_excluded": false
        }
      },
      "all_reacquisition_items": {
        "MRR": {
          "bootstrap_win_rate": 0.279383429672447,
          "ci95_high": 0.022742061335510277,
          "ci95_low": -0.018506211163076373,
          "count": 1038,
          "mean_delta": 0.002024729317390789,
          "zero_excluded": false
        },
        "false_confuser_rate": {
          "bootstrap_win_rate": 0.17148362235067438,
          "ci95_high": 0.041425818882466284,
          "ci95_low": -0.027938342967244702,
          "count": 1038,
          "mean_delta": 0.005780346820809248,
          "zero_excluded": false
        },
        "false_reacquisition_rate": {
          "bootstrap_win_rate": 0.17148362235067438,
          "ci95_high": 0.041425818882466284,
          "ci95_low": -0.027938342967244702,
          "count": 1038,
          "mean_delta": 0.005780346820809248,
          "zero_excluded": false
        },
        "top1": {
          "bootstrap_win_rate": 0.17148362235067438,
          "ci95_high": 0.041425818882466284,
          "ci95_low": -0.027938342967244702,
          "count": 1038,
          "mean_delta": 0.005780346820809248,
          "zero_excluded": false
        }
      },
      "appearance_similar_confuser": {
        "MRR": {
          "bootstrap_win_rate": 0.23397435897435898,
          "ci95_high": -0.005053164428164431,
          "ci95_low": -0.05952889702889704,
          "count": 624,
          "mean_delta": -0.03221100036003883,
          "zero_excluded": true
        },
        "false_confuser_rate": {
          "bootstrap_win_rate": 0.14583333333333334,
          "ci95_high": 0.004807692307692308,
          "ci95_low": -0.08493589743589744,
          "count": 624,
          "mean_delta": -0.038461538461538464,
          "zero_excluded": false
        },
        "false_reacquisition_rate": {
          "bootstrap_win_rate": 0.14583333333333334,
          "ci95_high": 0.004807692307692308,
          "ci95_low": -0.08493589743589744,
          "count": 624,
          "mean_delta": -0.038461538461538464,
          "zero_excluded": false
        },
        "top1": {
          "bootstrap_win_rate": 0.14583333333333334,
          "ci95_high": 0.004807692307692308,
          "ci95_low": -0.08493589743589744,
          "count": 624,
          "mean_delta": -0.038461538461538464,
          "zero_excluded": false
        }
      },
      "crossing_or_overlap_confuser": {
        "MRR": {
          "bootstrap_win_rate": 0.410958904109589,
          "ci95_high": 0.09684760604802296,
          "ci95_low": 0.026966432930300308,
          "count": 438,
          "mean_delta": 0.061761801441670414,
          "zero_excluded": true
        },
        "false_confuser_rate": {
          "bootstrap_win_rate": 0.2420091324200913,
          "ci95_high": 0.1643835616438356,
          "ci95_low": 0.04794520547945205,
          "count": 438,
          "mean_delta": 0.1050228310502283,
          "zero_excluded": true
        },
        "false_reacquisition_rate": {
          "bootstrap_win_rate": 0.2420091324200913,
          "ci95_high": 0.1643835616438356,
          "ci95_low": 0.04794520547945205,
          "count": 438,
          "mean_delta": 0.1050228310502283,
          "zero_excluded": true
        },
        "top1": {
          "bootstrap_win_rate": 0.2420091324200913,
          "ci95_high": 0.1643835616438356,
          "ci95_low": 0.04794520547945205,
          "count": 438,
          "mean_delta": 0.1050228310502283,
          "zero_excluded": true
        }
      },
      "long_gap_persistence": {
        "MRR": {
          "bootstrap_win_rate": 0.2289156626506024,
          "ci95_high": -0.02173933830560337,
          "ci95_low": -0.07030742015681775,
          "count": 498,
          "mean_delta": -0.0453241537578887,
          "zero_excluded": true
        },
        "false_confuser_rate": {
          "bootstrap_win_rate": 0.08032128514056225,
          "ci95_high": -0.03614457831325301,
          "ci95_low": -0.12248995983935743,
          "count": 498,
          "mean_delta": -0.08032128514056225,
          "zero_excluded": true
        },
        "false_reacquisition_rate": {
          "bootstrap_win_rate": 0.08032128514056225,
          "ci95_high": -0.03614457831325301,
          "ci95_low": -0.12248995983935743,
          "count": 498,
          "mean_delta": -0.08032128514056225,
          "zero_excluded": true
        },
        "top1": {
          "bootstrap_win_rate": 0.08032128514056225,
          "ci95_high": -0.03614457831325301,
          "ci95_low": -0.12248995983935743,
          "count": 498,
          "mean_delta": -0.08032128514056225,
          "zero_excluded": true
        }
      },
      "occlusion_and_long_gap": {
        "MRR": {
          "bootstrap_win_rate": 0.2289156626506024,
          "ci95_high": -0.02173933830560337,
          "ci95_low": -0.07030742015681775,
          "count": 498,
          "mean_delta": -0.0453241537578887,
          "zero_excluded": true
        },
        "false_confuser_rate": {
          "bootstrap_win_rate": 0.08032128514056225,
          "ci95_high": -0.03614457831325301,
          "ci95_low": -0.12248995983935743,
          "count": 498,
          "mean_delta": -0.08032128514056225,
          "zero_excluded": true
        },
        "false_reacquisition_rate": {
          "bootstrap_win_rate": 0.08032128514056225,
          "ci95_high": -0.03614457831325301,
          "ci95_low": -0.12248995983935743,
          "count": 498,
          "mean_delta": -0.08032128514056225,
          "zero_excluded": true
        },
        "top1": {
          "bootstrap_win_rate": 0.08032128514056225,
          "ci95_high": -0.03614457831325301,
          "ci95_low": -0.12248995983935743,
          "count": 498,
          "mean_delta": -0.08032128514056225,
          "zero_excluded": true
        }
      },
      "occlusion_reappearance": {
        "MRR": {
          "bootstrap_win_rate": 0.279383429672447,
          "ci95_high": 0.022742061335510277,
          "ci95_low": -0.018506211163076373,
          "count": 1038,
          "mean_delta": 0.002024729317390789,
          "zero_excluded": false
        },
        "false_confuser_rate": {
          "bootstrap_win_rate": 0.17148362235067438,
          "ci95_high": 0.041425818882466284,
          "ci95_low": -0.027938342967244702,
          "count": 1038,
          "mean_delta": 0.005780346820809248,
          "zero_excluded": false
        },
        "false_reacquisition_rate": {
          "bootstrap_win_rate": 0.17148362235067438,
          "ci95_high": 0.041425818882466284,
          "ci95_low": -0.027938342967244702,
          "count": 1038,
          "mean_delta": 0.005780346820809248,
          "zero_excluded": false
        },
        "top1": {
          "bootstrap_win_rate": 0.17148362235067438,
          "ci95_high": 0.041425818882466284,
          "ci95_low": -0.027938342967244702,
          "count": 1038,
          "mean_delta": 0.005780346820809248,
          "zero_excluded": false
        }
      },
      "spatially_close_confuser": {
        "MRR": {
          "bootstrap_win_rate": 0.33045977011494254,
          "ci95_high": 0.05542385349856614,
          "ci95_low": -0.0005350759957831434,
          "count": 696,
          "mean_delta": 0.02693521138892203,
          "zero_excluded": false
        },
        "false_confuser_rate": {
          "bootstrap_win_rate": 0.20402298850574713,
          "ci95_high": 0.09626436781609195,
          "ci95_low": 0.004310344827586207,
          "count": 696,
          "mean_delta": 0.04885057471264368,
          "zero_excluded": true
        },
        "false_reacquisition_rate": {
          "bootstrap_win_rate": 0.20402298850574713,
          "ci95_high": 0.09626436781609195,
          "ci95_low": 0.004310344827586207,
          "count": 696,
          "mean_delta": 0.04885057471264368,
          "zero_excluded": true
        },
        "top1": {
          "bootstrap_win_rate": 0.20402298850574713,
          "ci95_high": 0.09626436781609195,
          "ci95_low": 0.004310344827586207,
          "count": 696,
          "mean_delta": 0.04885057471264368,
          "zero_excluded": true
        }
      }
    },
    "full_trace_belief_vs_legacysem": {
      "OOD_confuser": {
        "MRR": {
          "bootstrap_win_rate": 0.6048109965635738,
          "ci95_high": 0.26403593706528905,
          "ci95_low": 0.20012363963123103,
          "count": 582,
          "mean_delta": 0.2320249788527858,
          "zero_excluded": true
        },
        "false_confuser_rate": {
          "bootstrap_win_rate": 0.38831615120274915,
          "ci95_high": 0.35051546391752575,
          "ci95_low": 0.24914089347079038,
          "count": 582,
          "mean_delta": 0.3006872852233677,
          "zero_excluded": true
        },
        "false_reacquisition_rate": {
          "bootstrap_win_rate": 0.38831615120274915,
          "ci95_high": 0.35051546391752575,
          "ci95_low": 0.24914089347079038,
          "count": 582,
          "mean_delta": 0.3006872852233677,
          "zero_excluded": true
        },
        "top1": {
          "bootstrap_win_rate": 0.38831615120274915,
          "ci95_high": 0.35051546391752575,
          "ci95_low": 0.24914089347079038,
          "count": 582,
          "mean_delta": 0.3006872852233677,
          "zero_excluded": true
        }
      },
      "all_reacquisition_items": {
        "MRR": {
          "bootstrap_win_rate": 0.6339113680154143,
          "ci95_high": 0.2799332110887868,
          "ci95_low": 0.23012586097309198,
          "count": 1038,
          "mean_delta": 0.2551675742371631,
          "zero_excluded": true
        },
        "false_confuser_rate": {
          "bootstrap_win_rate": 0.4229287090558767,
          "ci95_high": 0.3786127167630058,
          "ci95_low": 0.302504816955684,
          "count": 1038,
          "mean_delta": 0.3420038535645472,
          "zero_excluded": true
        },
        "false_reacquisition_rate": {
          "bootstrap_win_rate": 0.4229287090558767,
          "ci95_high": 0.3786127167630058,
          "ci95_low": 0.302504816955684,
          "count": 1038,
          "mean_delta": 0.3420038535645472,
          "zero_excluded": true
        },
        "top1": {
          "bootstrap_win_rate": 0.4229287090558767,
          "ci95_high": 0.3786127167630058,
          "ci95_low": 0.302504816955684,
          "count": 1038,
          "mean_delta": 0.3420038535645472,
          "zero_excluded": true
        }
      },
      "appearance_similar_confuser": {
        "MRR": {
          "bootstrap_win_rate": 0.5865384615384616,
          "ci95_high": 0.23293885601577907,
          "ci95_low": 0.16724972410068564,
          "count": 624,
          "mean_delta": 0.19980731074481076,
          "zero_excluded": true
        },
        "false_confuser_rate": {
          "bootstrap_win_rate": 0.38782051282051283,
          "ci95_high": 0.32532051282051283,
          "ci95_low": 0.22275641025641027,
          "count": 624,
          "mean_delta": 0.27403846153846156,
          "zero_excluded": true
        },
        "false_reacquisition_rate": {
          "bootstrap_win_rate": 0.38782051282051283,
          "ci95_high": 0.32532051282051283,
          "ci95_low": 0.22275641025641027,
          "count": 624,
          "mean_delta": 0.27403846153846156,
          "zero_excluded": true
        },
        "top1": {
          "bootstrap_win_rate": 0.38782051282051283,
          "ci95_high": 0.32532051282051283,
          "ci95_low": 0.22275641025641027,
          "count": 624,
          "mean_delta": 0.27403846153846156,
          "zero_excluded": true
        }
      },
      "crossing_or_overlap_confuser": {
        "MRR": {
          "bootstrap_win_rate": 0.5639269406392694,
          "ci95_high": 0.26036739083001503,
          "ci95_low": 0.1773805261233678,
          "count": 438,
          "mean_delta": 0.21825912908677542,
          "zero_excluded": true
        },
        "false_confuser_rate": {
          "bootstrap_win_rate": 0.3561643835616438,
          "ci95_high": 0.3356164383561644,
          "ci95_low": 0.22146118721461186,
          "count": 438,
          "mean_delta": 0.2785388127853881,
          "zero_excluded": true
        },
        "false_reacquisition_rate": {
          "bootstrap_win_rate": 0.3561643835616438,
          "ci95_high": 0.3356164383561644,
          "ci95_low": 0.22146118721461186,
          "count": 438,
          "mean_delta": 0.2785388127853881,
          "zero_excluded": true
        },
        "top1": {
          "bootstrap_win_rate": 0.3561643835616438,
          "ci95_high": 0.3356164383561644,
          "ci95_low": 0.22146118721461186,
          "count": 438,
          "mean_delta": 0.2785388127853881,
          "zero_excluded": true
        }
      },
      "long_gap_persistence": {
        "MRR": {
          "bootstrap_win_rate": 0.6104417670682731,
          "ci95_high": 0.23238987696819022,
          "ci95_low": 0.16440364633135718,
          "count": 498,
          "mean_delta": 0.198799961751769,
          "zero_excluded": true
        },
        "false_confuser_rate": {
          "bootstrap_win_rate": 0.3795180722891566,
          "ci95_high": 0.3493975903614458,
          "ci95_low": 0.23694779116465864,
          "count": 498,
          "mean_delta": 0.29518072289156627,
          "zero_excluded": true
        },
        "false_reacquisition_rate": {
          "bootstrap_win_rate": 0.3795180722891566,
          "ci95_high": 0.3493975903614458,
          "ci95_low": 0.23694779116465864,
          "count": 498,
          "mean_delta": 0.29518072289156627,
          "zero_excluded": true
        },
        "top1": {
          "bootstrap_win_rate": 0.3795180722891566,
          "ci95_high": 0.3493975903614458,
          "ci95_low": 0.23694779116465864,
          "count": 498,
          "mean_delta": 0.29518072289156627,
          "zero_excluded": true
        }
      },
      "occlusion_and_long_gap": {
        "MRR": {
          "bootstrap_win_rate": 0.6104417670682731,
          "ci95_high": 0.23238987696819022,
          "ci95_low": 0.16440364633135718,
          "count": 498,
          "mean_delta": 0.198799961751769,
          "zero_excluded": true
        },
        "false_confuser_rate": {
          "bootstrap_win_rate": 0.3795180722891566,
          "ci95_high": 0.3493975903614458,
          "ci95_low": 0.23694779116465864,
          "count": 498,
          "mean_delta": 0.29518072289156627,
          "zero_excluded": true
        },
        "false_reacquisition_rate": {
          "bootstrap_win_rate": 0.3795180722891566,
          "ci95_high": 0.3493975903614458,
          "ci95_low": 0.23694779116465864,
          "count": 498,
          "mean_delta": 0.29518072289156627,
          "zero_excluded": true
        },
        "top1": {
          "bootstrap_win_rate": 0.3795180722891566,
          "ci95_high": 0.3493975903614458,
          "ci95_low": 0.23694779116465864,
          "count": 498,
          "mean_delta": 0.29518072289156627,
          "zero_excluded": true
        }
      },
      "occlusion_reappearance": {
        "MRR": {
          "bootstrap_win_rate": 0.6339113680154143,
          "ci95_high": 0.2799332110887868,
          "ci95_low": 0.23012586097309198,
          "count": 1038,
          "mean_delta": 0.2551675742371631,
          "zero_excluded": true
        },
        "false_confuser_rate": {
          "bootstrap_win_rate": 0.4229287090558767,
          "ci95_high": 0.3786127167630058,
          "ci95_low": 0.302504816955684,
          "count": 1038,
          "mean_delta": 0.3420038535645472,
          "zero_excluded": true
        },
        "false_reacquisition_rate": {
          "bootstrap_win_rate": 0.4229287090558767,
          "ci95_high": 0.3786127167630058,
          "ci95_low": 0.302504816955684,
          "count": 1038,
          "mean_delta": 0.3420038535645472,
          "zero_excluded": true
        },
        "top1": {
          "bootstrap_win_rate": 0.4229287090558767,
          "ci95_high": 0.3786127167630058,
          "ci95_low": 0.302504816955684,
          "count": 1038,
          "mean_delta": 0.3420038535645472,
          "zero_excluded": true
        }
      },
      "spatially_close_confuser": {
        "MRR": {
          "bootstrap_win_rate": 0.6637931034482759,
          "ci95_high": 0.2864799526830188,
          "ci95_low": 0.2259159946396324,
          "count": 696,
          "mean_delta": 0.25580820903268203,
          "zero_excluded": true
        },
        "false_confuser_rate": {
          "bootstrap_win_rate": 0.3735632183908046,
          "ci95_high": 0.33764367816091956,
          "ci95_low": 0.24568965517241378,
          "count": 696,
          "mean_delta": 0.2916666666666667,
          "zero_excluded": true
        },
        "false_reacquisition_rate": {
          "bootstrap_win_rate": 0.3735632183908046,
          "ci95_high": 0.33764367816091956,
          "ci95_low": 0.24568965517241378,
          "count": 696,
          "mean_delta": 0.2916666666666667,
          "zero_excluded": true
        },
        "top1": {
          "bootstrap_win_rate": 0.3735632183908046,
          "ci95_high": 0.33764367816091956,
          "ci95_low": 0.24568965517241378,
          "count": 696,
          "mean_delta": 0.2916666666666667,
          "zero_excluded": true
        }
      }
    }
  },
  "created_at": "2026-04-25T12:19:51.069755+00:00",
  "positive_delta_policy": "For top1/MRR, positive means full_trace_belief minus baseline. For false rates, positive means baseline false rate minus full_trace_belief false rate.",
  "source_eval": "reports/stwm_reacquisition_v2_eval_20260425.json"
}