{
  "audit_name": "stwm_fullscale_semantic_trace_world_model_v1_train_launch",
  "candidate_scorer_used": false,
  "command_path": "code/stwm/tools/run_fullscale_semantic_trace_world_model_v1_20260428.sh",
  "dynamic_trainable_params": 0,
  "feedback_used": false,
  "future_candidate_leakage": false,
  "gpu_ids": "default_cuda_visible_devices",
  "launched_at_unix": 1777527093.931078,
  "launched_sessions": [
    "stwm_fullscale_v1_20260428"
  ],
  "log_path": "outputs/logs/stwm_fullscale_semantic_trace_world_model_v1_20260428.log",
  "prototype_counts": [
    32,
    64
  ],
  "seeds": [
    42,
    123,
    456,
    789,
    1001
  ],
  "stage1_trainable_param_count": 0,
  "status": "launched_background_pipeline",
  "steps": 5000,
  "trace_backbone_trainable": false
}
