{
  "STWM_beats_same_output_baselines": false,
  "audit_name": "stwm_final_cvpr_aaai_readiness_v2",
  "baseline_suite_completed": false,
  "core_main_result_status": {
    "changed_gain_CI_excludes_zero_mixed": true,
    "changed_gain_CI_excludes_zero_vipseg": true,
    "changed_gain_CI_excludes_zero_vspw": true,
    "residual_beats_copy_mixed": true,
    "residual_beats_copy_vipseg": true,
    "residual_beats_copy_vspw": true,
    "semantic_field_branch_status": "main_contribution_candidate",
    "stable_copy_preserved": true,
    "trace_regression_detected": false
  },
  "density_scaling_completed": false,
  "horizon_scaling_completed": false,
  "horizon_scaling_positive": false,
  "lodo_completed": false,
  "lodo_positive": false,
  "model_scaling_completed": false,
  "model_scaling_positive": false,
  "next_step_choice": "run_missing_scaling",
  "prototype_scaling_completed": true,
  "ready_for_cvpr_aaai_main": "unclear",
  "ready_for_overleaf": true,
  "remaining_risks": [
    "LODO remains incomplete.",
    "Model-size scaling remains incomplete.",
    "Horizon scaling remains incomplete.",
    "Trace-density scaling remains incomplete.",
    "Same-output free-rollout baseline suite remains incomplete.",
    "Final MP4/GIF qualitative videos are not ready.",
    "Prototype vocabulary justification is good for C32/C64 but requested C16 evidence is still absent."
  ],
  "selected_C_justified": true,
  "video_visualization_ready": false
}
